odoo8_addon_l10n_nl_normalize_zip-8.0.1.0.0-py2.7-nspkg.pth
odoo_addons/l10n_nl_normalize_zip/__openerp__.py
odoo_addons/l10n_nl_normalize_zip/__init__.py
odoo_addons/l10n_nl_normalize_zip/README.rst
odoo_addons/l10n_nl_normalize_zip/models/res_partner.py
odoo_addons/l10n_nl_normalize_zip/models/__init__.py
odoo_addons/l10n_nl_normalize_zip/tests/__init__.py
odoo_addons/l10n_nl_normalize_zip/tests/test_l10n_nl_normalize_zip.py
odoo_addons/l10n_nl_normalize_zip/static/description/icon.png
odoo8_addon_l10n_nl_normalize_zip-8.0.1.0.0.dist-info/top_level.txt
odoo8_addon_l10n_nl_normalize_zip-8.0.1.0.0.dist-info/WHEEL
odoo8_addon_l10n_nl_normalize_zip-8.0.1.0.0.dist-info/RECORD
odoo8_addon_l10n_nl_normalize_zip-8.0.1.0.0.dist-info/metadata.json
odoo8_addon_l10n_nl_normalize_zip-8.0.1.0.0.dist-info/DESCRIPTION.rst
odoo8_addon_l10n_nl_normalize_zip-8.0.1.0.0.dist-info/METADATA
odoo8_addon_l10n_nl_normalize_zip-8.0.1.0.0.dist-info/namespace_packages.txt
