Metadata-Version: 2.0
Name: odoo8-addon-l10n-nl-normalize-zip
Version: 8.0.1.0.0
Summary: This module forces zip codes to look like 0000 XX
Home-page: UNKNOWN
Author: Therp BV,Odoo Community Association (OCA)
Author-email: support@odoo-community.org
License: AGPL-3
Platform: UNKNOWN
Requires-Dist: odoo (<9.0a,>=8.0a)
Requires-Dist: odoo8-addon-field-char-transformed
Classifier: Programming Language :: Python :: 2.7
Classifier: Framework :: Odoo
Classifier: License :: OSI Approved :: GNU Affero General Public License v3
